vedro_screenshot_matcher/__init__.py
vedro_screenshot_matcher/_scheduler.py
vedro_screenshot_matcher/_screenshot_asserts.py
vedro_screenshot_matcher/_screenshot_matcher.py
vedro_screenshot_matcher/_screenshot_matcher_plugin.py
vedro_screenshot_matcher-0.1.0.dist-info/METADATA
vedro_screenshot_matcher-0.1.0.dist-info/WHEEL
vedro_screenshot_matcher-0.1.0.dist-info/top_level.txt
vedro_screenshot_matcher-0.1.0.dist-info/RECORD
