Metadata-Version: 2.1
Name: vedro-screenshot-matcher
Version: 0.1.0
Summary: Playwright plugin for matching screenshots with Vedro Testing Framework
Home-page: https://github.com/MashaJing/vedro-screenshot-matcher
Author: MashaJing
Author-email: mdzekh23032000a@gmail.com
License: Apache-2.0
Project-URL: GitHub, https://github.com/MashaJing/vedro-screenshot-matcher
Classifier: License :: OSI Approved :: Apache Software License
Classifier: Programming Language :: Python :: 3.9
Classifier: Programming Language :: Python :: 3.10
Classifier: Programming Language :: Python :: 3.11
Requires-Python: >=3.9
Requires-Dist: vedro <2.0,>=1.7
Requires-Dist: playwright <2.0,>=1.21
Requires-Dist: pixelmatch <1.0,>=0.3
Requires-Dist: Pillow <11.0,>=10.0
Requires-Dist: rtry ==1.4.1
Requires-Dist: pyqt5 <5.16
Requires-Dist: pyqtwebengine <5.16
